suryamv_cv/__init__.py
suryamv_cv/histogram_equalization.py
suryamv_cv/image_filters.py
suryamv_cv/lowpasshighpass.py
suryamv_cv/point_operations.py
suryamv_cv-0.1.0.dist-info/LICENSE
suryamv_cv-0.1.0.dist-info/METADATA
suryamv_cv-0.1.0.dist-info/WHEEL
suryamv_cv-0.1.0.dist-info/top_level.txt
suryamv_cv-0.1.0.dist-info/RECORD
