Metadata-Version: 2.2
Name: suryamv-cv
Version: 0.1.0
Summary: A computer vision package with various image filtering and processing modules.
Author: M.V Surya
Author-email: suryamv0507@gmail.com
Classifier: Programming Language :: Python :: 3
Classifier: Operating System :: OS Independent
Classifier: License :: OSI Approved :: MIT License
Classifier: Topic :: Software Development :: Libraries :: Python Modules
Classifier: Intended Audience :: Developers
Requires-Python: >=3.6
License-File: LICENSE
Requires-Dist: numpy
Requires-Dist: opencv-python
Dynamic: author
Dynamic: author-email
Dynamic: classifier
Dynamic: requires-dist
Dynamic: requires-python
Dynamic: summary
